<?xml version="1.0" encoding="utf-8" ?>
<c2layout>
    <name>Ciclope - Scene 2</name>
    <sid>821168508343233</sid>
    <event-sheet>Ciclope - Scene 2 Events</event-sheet>
    <size>
        <width>1280</width>
        <height>720</height>
    </size>
    <margins>
        <horizontal>500</horizontal>
        <vertical>500</vertical>
    </margins>
    <unbounded-scrolling>0</unbounded-scrolling>
    <layers>
        <layer name="Layer 0" sid="355568740848476">
            <initially-visible>1</initially-visible>
            <background-color>255,255,255</background-color>
            <transparent>0</transparent>
            <parallax>
                <x>1</x>
                <y>1</y>
            </parallax>
            <zoom-rate>1</zoom-rate>
            <opacity>1</opacity>
            <force-own-texture>0</force-own-texture>
            <global>0</global>
            <use-render-cells>0</use-render-cells>
            <blend-mode>0</blend-mode>
            <effect-fallback>0</effect-fallback>
            <instances>
                <instance type="spr_background" uid="71">
                    <properties>
                        <initial-visibility>Visible</initial-visibility>
                        <initial-animation>CiclopeScene1</initial-animation>
                        <initial-frame>0</initial-frame>
                        <collisions>Enabled</collisions>
                    </properties>
                    <blend-mode>0</blend-mode>
                    <effect-fallback>0</effect-fallback>
                    <world>
                        <x>0</x>
                        <y>0</y>
                        <z>0</z>
                        <width>1294.144042969</width>
                        <height>727.956115723</height>
                        <depth>0</depth>
                        <hotspotX>0</hotspotX>
                        <hotspotY>0</hotspotY>
                        <angle>0</angle>
                        <opacity>1</opacity>
                    </world>
                </instance>
                <instance type="spr_player" uid="72">
                    <properties>
                        <initial-visibility>Visible</initial-visibility>
                        <initial-animation>Default</initial-animation>
                        <initial-frame>0</initial-frame>
                        <collisions>Enabled</collisions>
                    </properties>
                    <instance-variables>
                        <canAttack>true</canAttack>
                        <specialAttackDamage>0</specialAttackDamage>
                    </instance-variables>
                    <behavior-instances>
                        <behavior-instance type="8Direction">
                            <properties>
                                <max-speed>200</max-speed>
                                <acceleration>600</acceleration>
                                <deceleration>500</deceleration>
                                <directions>8 directions</directions>
                                <set-angle>No</set-angle>
                                <default-controls>No</default-controls>
                                <initial-state>Enabled</initial-state>
                            </properties>
                        </behavior-instance>
                        <behavior-instance type="BoundToLayout">
                            <properties>
                                <bound-by>Edge</bound-by>
                            </properties>
                        </behavior-instance>
                    </behavior-instances>
                    <blend-mode>0</blend-mode>
                    <effect-fallback>0</effect-fallback>
                    <world>
                        <x>64</x>
                        <y>384</y>
                        <z>0</z>
                        <width>22.627416611</width>
                        <height>45.254833221</height>
                        <depth>0</depth>
                        <hotspotX>0.5</hotspotX>
                        <hotspotY>0.5</hotspotY>
                        <angle>0</angle>
                        <opacity>1</opacity>
                    </world>
                </instance>
                <instance type="txt_playerAttackUses" uid="78">
                    <properties>
                        <text>Ataques: 100</text>
                        <initial-visibility>Visible</initial-visibility>
                        <font>Arial,-21,400,0</font>
                        <color>0,0,0</color>
                        <horizontal-alignment>Left</horizontal-alignment>
                        <vertical-alignment>Top</vertical-alignment>
                        <hotspot>Top-left</hotspot>
                        <wrapping>Word</wrapping>
                        <line-height>0</line-height>
                    </properties>
                    <blend-mode>0</blend-mode>
                    <effect-fallback>0</effect-fallback>
                    <world>
                        <x>53</x>
                        <y>1</y>
                        <z>0</z>
                        <width>156</width>
                        <height>30</height>
                        <depth>0</depth>
                        <hotspotX>0</hotspotX>
                        <hotspotY>0</hotspotY>
                        <angle>0</angle>
                        <opacity>1</opacity>
                    </world>
                </instance>
                <instance type="pgb_playerSpecialAttackProgress" uid="79">
                    <properties>
                        <value>0</value>
                        <maximum>100</maximum>
                        <tooltip></tooltip>
                        <initial-visibility>Visible</initial-visibility>
                        <id-optional></id-optional>
                    </properties>
                    <blend-mode>0</blend-mode>
                    <effect-fallback>0</effect-fallback>
                    <world>
                        <x>576</x>
                        <y>0</y>
                        <z>0</z>
                        <width>200</width>
                        <height>32</height>
                        <depth>0</depth>
                        <hotspotX>0</hotspotX>
                        <hotspotY>0</hotspotY>
                    </world>
                </instance>
                <instance type="txt_playerTime" uid="80">
                    <properties>
                        <text>Tempo: 0</text>
                        <initial-visibility>Visible</initial-visibility>
                        <font>Arial,-21,400,0</font>
                        <color>0,0,0</color>
                        <horizontal-alignment>Left</horizontal-alignment>
                        <vertical-alignment>Top</vertical-alignment>
                        <hotspot>Top-left</hotspot>
                        <wrapping>Word</wrapping>
                        <line-height>0</line-height>
                    </properties>
                    <blend-mode>0</blend-mode>
                    <effect-fallback>0</effect-fallback>
                    <world>
                        <x>1088</x>
                        <y>0</y>
                        <z>0</z>
                        <width>160</width>
                        <height>30</height>
                        <depth>0</depth>
                        <hotspotX>0</hotspotX>
                        <hotspotY>0</hotspotY>
                        <angle>0</angle>
                        <opacity>1</opacity>
                    </world>
                </instance>
                <instance type="spr_playerSpecialAttackIcon" uid="81">
                    <properties>
                        <initial-visibility>Visible</initial-visibility>
                        <initial-animation>CiclopeInactive</initial-animation>
                        <initial-frame>0</initial-frame>
                        <collisions>Enabled</collisions>
                    </properties>
                    <blend-mode>0</blend-mode>
                    <effect-fallback>0</effect-fallback>
                    <world>
                        <x>512</x>
                        <y>0</y>
                        <z>0</z>
                        <width>32</width>
                        <height>32</height>
                        <depth>0</depth>
                        <hotspotX>0</hotspotX>
                        <hotspotY>0</hotspotY>
                        <angle>0</angle>
                        <opacity>1</opacity>
                    </world>
                </instance>
                <instance type="spr_playerHealth" uid="91">
                    <properties>
                        <initial-visibility>Visible</initial-visibility>
                        <initial-animation>Green</initial-animation>
                        <initial-frame>0</initial-frame>
                        <collisions>Enabled</collisions>
                    </properties>
                    <blend-mode>0</blend-mode>
                    <effect-fallback>0</effect-fallback>
                    <world>
                        <x>225.199981689</x>
                        <y>-61</y>
                        <z>0</z>
                        <width>32</width>
                        <height>8</height>
                        <depth>0</depth>
                        <hotspotX>0</hotspotX>
                        <hotspotY>0.5</hotspotY>
                        <angle>0</angle>
                        <opacity>1</opacity>
                    </world>
                </instance>
                <instance type="spr_playerHealthBar" uid="92">
                    <properties>
                        <initial-visibility>Visible</initial-visibility>
                        <initial-animation>Default</initial-animation>
                        <initial-frame>0</initial-frame>
                        <collisions>Enabled</collisions>
                    </properties>
                    <blend-mode>0</blend-mode>
                    <effect-fallback>0</effect-fallback>
                    <world>
                        <x>193.199981689</x>
                        <y>-61</y>
                        <z>0</z>
                        <width>34</width>
                        <height>11</height>
                        <depth>0</depth>
                        <hotspotX>0.5</hotspotX>
                        <hotspotY>0.545454562</hotspotY>
                        <angle>0</angle>
                        <opacity>1</opacity>
                    </world>
                </instance>
                <instance type="spr_gokuBasicAttack" uid="93">
                    <properties>
                        <initial-visibility>Visible</initial-visibility>
                        <initial-animation>Default</initial-animation>
                        <initial-frame>0</initial-frame>
                        <collisions>Enabled</collisions>
                    </properties>
                    <instance-variables>
                        <damage>20</damage>
                    </instance-variables>
                    <behavior-instances>
                        <behavior-instance type="DestroyOutsideLayout" />
                        <behavior-instance type="Bullet">
                            <properties>
                                <speed>400</speed>
                                <acceleration>0</acceleration>
                                <gravity>0</gravity>
                                <bounce-off-solids>No</bounce-off-solids>
                                <set-angle>Yes</set-angle>
                                <initial-state>Enabled</initial-state>
                            </properties>
                        </behavior-instance>
                    </behavior-instances>
                    <blend-mode>0</blend-mode>
                    <effect-fallback>0</effect-fallback>
                    <world>
                        <x>641.199951172</x>
                        <y>-61</y>
                        <z>0</z>
                        <width>26</width>
                        <height>26</height>
                        <depth>0</depth>
                        <hotspotX>0.5</hotspotX>
                        <hotspotY>0.5</hotspotY>
                        <angle>0</angle>
                        <opacity>1</opacity>
                    </world>
                </instance>
                <instance type="txt_playerName" uid="94">
                    <properties>
                        <text>Text</text>
                        <initial-visibility>Visible</initial-visibility>
                        <font>Arial,-13,400,0</font>
                        <color>0,0,0</color>
                        <horizontal-alignment>Center</horizontal-alignment>
                        <vertical-alignment>Center</vertical-alignment>
                        <hotspot>Center</hotspot>
                        <wrapping>Word</wrapping>
                        <line-height>0</line-height>
                    </properties>
                    <blend-mode>0</blend-mode>
                    <effect-fallback>0</effect-fallback>
                    <world>
                        <x>449.199981689</x>
                        <y>-61</y>
                        <z>0</z>
                        <width>256</width>
                        <height>32</height>
                        <depth>0</depth>
                        <hotspotX>0.5</hotspotX>
                        <hotspotY>0.5</hotspotY>
                        <angle>0</angle>
                        <opacity>1</opacity>
                    </world>
                </instance>
                <instance type="spr_enemyRangedAttack" uid="95">
                    <properties>
                        <initial-visibility>Visible</initial-visibility>
                        <initial-animation>Default</initial-animation>
                        <initial-frame>0</initial-frame>
                        <collisions>Enabled</collisions>
                    </properties>
                    <behavior-instances>
                        <behavior-instance type="Bullet">
                            <properties>
                                <speed>300</speed>
                                <acceleration>0</acceleration>
                                <gravity>0</gravity>
                                <bounce-off-solids>No</bounce-off-solids>
                                <set-angle>Yes</set-angle>
                                <initial-state>Enabled</initial-state>
                            </properties>
                        </behavior-instance>
                        <behavior-instance type="DestroyOutsideLayout" />
                    </behavior-instances>
                    <blend-mode>0</blend-mode>
                    <effect-fallback>0</effect-fallback>
                    <world>
                        <x>321.199981689</x>
                        <y>-61</y>
                        <z>0</z>
                        <width>32</width>
                        <height>32</height>
                        <depth>0</depth>
                        <hotspotX>0.59375</hotspotX>
                        <hotspotY>0.34375</hotspotY>
                        <angle>0</angle>
                        <opacity>1</opacity>
                    </world>
                </instance>
                <instance type="spr_portal" uid="82">
                    <properties>
                        <initial-visibility>Visible</initial-visibility>
                        <initial-animation>xmen</initial-animation>
                        <initial-frame>0</initial-frame>
                        <collisions>Disabled</collisions>
                    </properties>
                    <instance-variables>
                        <enemiesLeft>5</enemiesLeft>
                    </instance-variables>
                    <blend-mode>0</blend-mode>
                    <effect-fallback>0</effect-fallback>
                    <world>
                        <x>928</x>
                        <y>672</y>
                        <z>0</z>
                        <width>64</width>
                        <height>64</height>
                        <depth>0</depth>
                        <hotspotX>0.5</hotspotX>
                        <hotspotY>0.5</hotspotY>
                        <angle>0</angle>
                        <opacity>1</opacity>
                    </world>
                </instance>
                <instance type="spr_enemyMelee" uid="102">
                    <properties>
                        <initial-visibility>Visible</initial-visibility>
                        <initial-animation>MercurioDown</initial-animation>
                        <initial-frame>0</initial-frame>
                        <collisions>Enabled</collisions>
                    </properties>
                    <instance-variables>
                        <health>100</health>
                        <canAttack>true</canAttack>
                    </instance-variables>
                    <behavior-instances>
                        <behavior-instance type="Solid">
                            <properties>
                                <initial-state>Enabled</initial-state>
                            </properties>
                        </behavior-instance>
                        <behavior-instance type="Bullet">
                            <properties>
                                <speed>100</speed>
                                <acceleration>0</acceleration>
                                <gravity>0</gravity>
                                <bounce-off-solids>No</bounce-off-solids>
                                <set-angle>No</set-angle>
                                <initial-state>Enabled</initial-state>
                            </properties>
                        </behavior-instance>
                    </behavior-instances>
                    <blend-mode>0</blend-mode>
                    <effect-fallback>0</effect-fallback>
                    <world>
                        <x>931.605407715</x>
                        <y>121.189758301</y>
                        <z>0</z>
                        <width>25.210834503</width>
                        <height>40.617458344</height>
                        <depth>0</depth>
                        <hotspotX>0.5</hotspotX>
                        <hotspotY>0.413793117</hotspotY>
                        <angle>0</angle>
                        <opacity>1</opacity>
                    </world>
                </instance>
                <instance type="spr_enemyMelee" uid="103">
                    <properties>
                        <initial-visibility>Visible</initial-visibility>
                        <initial-animation>MercurioDown</initial-animation>
                        <initial-frame>0</initial-frame>
                        <collisions>Enabled</collisions>
                    </properties>
                    <instance-variables>
                        <health>100</health>
                        <canAttack>true</canAttack>
                    </instance-variables>
                    <behavior-instances>
                        <behavior-instance type="Solid">
                            <properties>
                                <initial-state>Enabled</initial-state>
                            </properties>
                        </behavior-instance>
                        <behavior-instance type="Bullet">
                            <properties>
                                <speed>100</speed>
                                <acceleration>0</acceleration>
                                <gravity>0</gravity>
                                <bounce-off-solids>No</bounce-off-solids>
                                <set-angle>No</set-angle>
                                <initial-state>Enabled</initial-state>
                            </properties>
                        </behavior-instance>
                    </behavior-instances>
                    <blend-mode>0</blend-mode>
                    <effect-fallback>0</effect-fallback>
                    <world>
                        <x>1123.60546875</x>
                        <y>121.189758301</y>
                        <z>0</z>
                        <width>25.210834503</width>
                        <height>40.617458344</height>
                        <depth>0</depth>
                        <hotspotX>0.5</hotspotX>
                        <hotspotY>0.413793117</hotspotY>
                        <angle>0</angle>
                        <opacity>1</opacity>
                    </world>
                </instance>
                <instance type="spr_enemyMelee" uid="104">
                    <properties>
                        <initial-visibility>Visible</initial-visibility>
                        <initial-animation>MercurioDown</initial-animation>
                        <initial-frame>0</initial-frame>
                        <collisions>Enabled</collisions>
                    </properties>
                    <instance-variables>
                        <health>100</health>
                        <canAttack>true</canAttack>
                    </instance-variables>
                    <behavior-instances>
                        <behavior-instance type="Solid">
                            <properties>
                                <initial-state>Enabled</initial-state>
                            </properties>
                        </behavior-instance>
                        <behavior-instance type="Bullet">
                            <properties>
                                <speed>100</speed>
                                <acceleration>0</acceleration>
                                <gravity>0</gravity>
                                <bounce-off-solids>No</bounce-off-solids>
                                <set-angle>No</set-angle>
                                <initial-state>Enabled</initial-state>
                            </properties>
                        </behavior-instance>
                    </behavior-instances>
                    <blend-mode>0</blend-mode>
                    <effect-fallback>0</effect-fallback>
                    <world>
                        <x>1155.60546875</x>
                        <y>313.189758301</y>
                        <z>0</z>
                        <width>25.210834503</width>
                        <height>40.617458344</height>
                        <depth>0</depth>
                        <hotspotX>0.5</hotspotX>
                        <hotspotY>0.413793117</hotspotY>
                        <angle>0</angle>
                        <opacity>1</opacity>
                    </world>
                </instance>
                <instance type="spr_enemyMelee" uid="105">
                    <properties>
                        <initial-visibility>Visible</initial-visibility>
                        <initial-animation>MercurioDown</initial-animation>
                        <initial-frame>0</initial-frame>
                        <collisions>Enabled</collisions>
                    </properties>
                    <instance-variables>
                        <health>100</health>
                        <canAttack>true</canAttack>
                    </instance-variables>
                    <behavior-instances>
                        <behavior-instance type="Solid">
                            <properties>
                                <initial-state>Enabled</initial-state>
                            </properties>
                        </behavior-instance>
                        <behavior-instance type="Bullet">
                            <properties>
                                <speed>100</speed>
                                <acceleration>0</acceleration>
                                <gravity>0</gravity>
                                <bounce-off-solids>No</bounce-off-solids>
                                <set-angle>No</set-angle>
                                <initial-state>Enabled</initial-state>
                            </properties>
                        </behavior-instance>
                    </behavior-instances>
                    <blend-mode>0</blend-mode>
                    <effect-fallback>0</effect-fallback>
                    <world>
                        <x>1027.60546875</x>
                        <y>505.189758301</y>
                        <z>0</z>
                        <width>25.210834503</width>
                        <height>40.617458344</height>
                        <depth>0</depth>
                        <hotspotX>0.5</hotspotX>
                        <hotspotY>0.413793117</hotspotY>
                        <angle>0</angle>
                        <opacity>1</opacity>
                    </world>
                </instance>
                <instance type="spr_enemyRanged" uid="106">
                    <properties>
                        <initial-visibility>Visible</initial-visibility>
                        <initial-animation>JuggernautDown</initial-animation>
                        <initial-frame>0</initial-frame>
                        <collisions>Enabled</collisions>
                    </properties>
                    <instance-variables>
                        <health>80</health>
                    </instance-variables>
                    <behavior-instances>
                        <behavior-instance type="Solid">
                            <properties>
                                <initial-state>Enabled</initial-state>
                            </properties>
                        </behavior-instance>
                    </behavior-instances>
                    <blend-mode>0</blend-mode>
                    <effect-fallback>0</effect-fallback>
                    <world>
                        <x>1152</x>
                        <y>576</y>
                        <z>0</z>
                        <width>46</width>
                        <height>62</height>
                        <depth>0</depth>
                        <hotspotX>0.586956501</hotspotX>
                        <hotspotY>0.5</hotspotY>
                        <angle>0</angle>
                        <opacity>1</opacity>
                    </world>
                </instance>
                <instance type="spr_powerUp" uid="107">
                    <properties>
                        <initial-visibility>Visible</initial-visibility>
                        <initial-animation>Default</initial-animation>
                        <initial-frame>0</initial-frame>
                        <collisions>Enabled</collisions>
                    </properties>
                    <blend-mode>0</blend-mode>
                    <effect-fallback>0</effect-fallback>
                    <world>
                        <x>704</x>
                        <y>768</y>
                        <z>0</z>
                        <width>38</width>
                        <height>20</height>
                        <depth>0</depth>
                        <hotspotX>0.5</hotspotX>
                        <hotspotY>0.5</hotspotY>
                        <angle>0</angle>
                        <opacity>1</opacity>
                    </world>
                </instance>
            </instances>
            <effects />
        </layer>
    </layers>
    <nonworld-instances />
    <effects />
</c2layout>
